setup.py
Ecks.egg-info/PKG-INFO
Ecks.egg-info/SOURCES.txt
Ecks.egg-info/dependency_links.txt
Ecks.egg-info/requires.txt
Ecks.egg-info/top_level.txt
ecks/__init__.py
ecks/ecks.py
ecks/plugins/__init__.py
ecks/plugins/cpu.py
ecks/plugins/cpu_cores.py
ecks/plugins/disk.py
ecks/plugins/loadavg.py
ecks/plugins/memory.py
ecks/plugins/nic.py
ecks/plugins/os.py
ecks/plugins/processes.py
ecks/plugins/tcpconn.py
ecks/plugins/tcpstats.py
ecks/plugins/uptime.py
ecks/plugins/wincpu.py
ecks/plugins/winmemory.py