Metadata-Version: 1.1
Name: Ecks
Version: 0.10
Summary: Easy access to SNMP data
Home-page: http://github.com/cread/ecks
Author: Chris Read
Author-email: chris.read@gmail.com
License: Apache 2.0
Keywords: snmp monitoring
Platform: UNKNOWN
Classifier: Development Status :: 4 - Beta
Classifier: Intended Audience :: Developers
Classifier: Intended Audience :: System Administrators
Classifier: License :: OSI Approved :: Apache Software License
Classifier: Operating System :: OS Independent
Classifier: Programming Language :: Python
Classifier: Topic :: Internet
Classifier: Topic :: Software Development :: Libraries :: Python Modules
Classifier: Topic :: System :: Monitoring
